certspy/__init__.py
certspy/certspy.py
certspy-0.9.0.dist-info/LICENSE
certspy-0.9.0.dist-info/METADATA
certspy-0.9.0.dist-info/WHEEL
certspy-0.9.0.dist-info/entry_points.txt
certspy-0.9.0.dist-info/top_level.txt
certspy-0.9.0.dist-info/RECORD
