Metadata-Version: 2.1
Name: certspy
Version: 0.9.0
Summary: A Python client for the crt.sh website to retrieve subdomains information
Home-page: https://github.com/santosomar/certspy
Author: Omar Santos
Author-email: santosomar@gmail.com
License: BSD 3-Clause License
Platform: UNKNOWN
License-File: LICENSE
Requires-Dist: requests
